README.md
setup.py
json_wmctrl/__init__.py
json_wmctrl/main.py
json_wmctrl.egg-info/PKG-INFO
json_wmctrl.egg-info/SOURCES.txt
json_wmctrl.egg-info/dependency_links.txt
json_wmctrl.egg-info/entry_points.txt
json_wmctrl.egg-info/requires.txt
json_wmctrl.egg-info/top_level.txt