Metadata-Version: 2.1
Name: json-wmctrl
Version: 1.0.0
Summary: List X windows with json output
Home-page: https://github.com/talwrii/json-wmctrl
Author: @readwithai
Author-email: talwrii@gmail.com
License: MIT
Keywords: X,wmctrl,window manager
